{
  "N": "38",
  "Enun": "Sobre tipos de dados, é correto afirmar que:",
  "A": "Tipos booleanos são valores que são mantidos fixos pelo compilador.",
  "B": "O double é um tipo inteiro duplo com menor precisão do que o tipo inteiro.",
  "C": "A faixa de valores dos tipos inteiros tem somente dois elementos: um para verdadeiro e outro\n    para falso.",
  "D": "Uma conversão de tipos implícita consiste em uma modificação do tipo de dados executado,\n    automaticamente, pelo compilador.",
  "E": "Vetores, matrizes e ponteiros são exemplos de tipos de dados primitivos (básicos)."
}
